molbeam_fp/__init__.py
molbeam_fp/app.py
molbeam_fp/large_csv_to_parquet_chunks.py
molbeam_fp/molbeam.py
molbeam_fp/mole.py
molbeam_fp/process_smiles_to_fp_pq.py
molbeam_fp/similarity.py
molbeam_fp-0.1.2.dist-info/LICENSE
molbeam_fp-0.1.2.dist-info/METADATA
molbeam_fp-0.1.2.dist-info/WHEEL
molbeam_fp-0.1.2.dist-info/entry_points.txt
molbeam_fp-0.1.2.dist-info/top_level.txt
molbeam_fp-0.1.2.dist-info/RECORD
