Metadata-Version: 2.1
Name: molbeam-fp
Version: 0.1.2
Classifier: Development Status :: 3 - Alpha
Classifier: License :: OSI Approved :: MIT License
Classifier: Programming Language :: Python :: 3
Classifier: Programming Language :: Python :: 3.6
Classifier: Programming Language :: Python :: 3.7
Classifier: Programming Language :: Python :: 3.8
Classifier: Programming Language :: Python :: 3.9
License-File: LICENSE
Requires-Dist: pyarrow
Requires-Dist: duckdb
Requires-Dist: datamol
Requires-Dist: rdkit
Requires-Dist: pandas
